<?xml version="1.0" encoding="utf-8" ?>
<dwsync>
<file name="1.png" server="ftp.hinklemarine.com" local="131275118900582711" remote="131256209400000000" Dst="1" />
<file name="1s.png" server="ftp.hinklemarine.com" local="131275118900622674" remote="131256209400000000" Dst="1" />
<file name="2.png" server="ftp.hinklemarine.com" local="131275118902462630" remote="131256209400000000" Dst="1" />
<file name="2s.png" server="ftp.hinklemarine.com" local="131275118902502568" remote="131256209400000000" Dst="1" />
<file name="3.png" server="ftp.hinklemarine.com" local="131275118904787111" remote="131256209400000000" Dst="1" />
<file name="3s.png" server="ftp.hinklemarine.com" local="131275118904866548" remote="131256209400000000" Dst="1" />
<file name="4.png" server="ftp.hinklemarine.com" local="131275118907031875" remote="131256209400000000" Dst="1" />
<file name="pay-1.png" server="ftp.hinklemarine.com" local="131275118907186989" remote="131256209400000000" Dst="1" />
<file name="4s.png" server="ftp.hinklemarine.com" local="131275118907227091" remote="131256209400000000" Dst="1" />
<file name="pay-2.png" server="ftp.hinklemarine.com" local="131275118910505529" remote="131256209400000000" Dst="1" />
<file name="pay-3.png" server="ftp.hinklemarine.com" local="131275118910505529" remote="131256209400000000" Dst="1" />
<file name="pay-4.png" server="ftp.hinklemarine.com" local="131275118910585507" remote="131256209400000000" Dst="1" />
<file name="pay-6.png" server="ftp.hinklemarine.com" local="131275118913389175" remote="131256209400000000" Dst="1" />
<file name="pay-5.png" server="ftp.hinklemarine.com" local="131275118913428641" remote="131256209400000000" Dst="1" />
<file name="pay-7.png" server="ftp.hinklemarine.com" local="131275118913468706" remote="131256209400000000" Dst="1" />
<file name="pay-8.png" server="ftp.hinklemarine.com" local="131275118916674177" remote="131256209400000000" Dst="1" />
</dwsync>